testwizard/commands_mobile/AddCapabilityCommand.py
testwizard/commands_mobile/Android_SendKeyCodeCommand.py
testwizard/commands_mobile/ClearElementCommand.py
testwizard/commands_mobile/ClickElementCommand.py
testwizard/commands_mobile/ClickPositionCommand.py
testwizard/commands_mobile/CloseAppCommand.py
testwizard/commands_mobile/FindElementCommand.py
testwizard/commands_mobile/GetAppiumSettingsCommand.py
testwizard/commands_mobile/GetAppiumSettingsResult.py
testwizard/commands_mobile/GetElementAttributeCommand.py
testwizard/commands_mobile/GetElementAttributeResult.py
testwizard/commands_mobile/GetElementCommand.py
testwizard/commands_mobile/GetElementLocationCommand.py
testwizard/commands_mobile/GetElementLocationResult.py
testwizard/commands_mobile/GetElementResult.py
testwizard/commands_mobile/GetElementSizeCommand.py
testwizard/commands_mobile/GetElementsCommand.py
testwizard/commands_mobile/GetElementsResult.py
testwizard/commands_mobile/GetOrientationCommand.py
testwizard/commands_mobile/GetOrientationResult.py
testwizard/commands_mobile/GetScreenSizeCommand.py
testwizard/commands_mobile/GetSizeResult.py
testwizard/commands_mobile/GetSourceCommand.py
testwizard/commands_mobile/GetSourceResult.py
testwizard/commands_mobile/HideKeyboardCommand.py
testwizard/commands_mobile/InitDriverCommand.py
testwizard/commands_mobile/InitDriverResult.py
testwizard/commands_mobile/InputTextCommand.py
testwizard/commands_mobile/LaunchAppCommand.py
testwizard/commands_mobile/MultiTouch_AddCommand.py
testwizard/commands_mobile/MultiTouch_NewCommand.py
testwizard/commands_mobile/MultiTouch_PerformCommand.py
testwizard/commands_mobile/PinchCoordinatesCommand.py
testwizard/commands_mobile/PinchElementCommand.py
testwizard/commands_mobile/QuitDriverCommand.py
testwizard/commands_mobile/RemoveAppCommand.py
testwizard/commands_mobile/ResetAppCommand.py
testwizard/commands_mobile/RunAppInBackgroundCommand.py
testwizard/commands_mobile/ScreenShotJPGCommand.py
testwizard.commands_mobile-3.8.1.dist-info/LICENSE.txt
testwizard.commands_mobile-3.8.1.dist-info/METADATA
testwizard.commands_mobile-3.8.1.dist-info/WHEEL
testwizard.commands_mobile-3.8.1.dist-info/top_level.txt
testwizard.commands_mobile-3.8.1.dist-info/RECORD
